scrolltext/__init__.py
scrolltext/cli.py
scrolltext/config.py
scrolltext/cursestext.py
scrolltext/getchtimeout.py
scrolltext/linescroller.py
scrolltext/utils.py
scrolltext-0.0.11.dist-info/LICENSE
scrolltext-0.0.11.dist-info/METADATA
scrolltext-0.0.11.dist-info/WHEEL
scrolltext-0.0.11.dist-info/entry_points.txt
scrolltext-0.0.11.dist-info/top_level.txt
scrolltext-0.0.11.dist-info/RECORD
