Metadata-Version: 2.1
Name: scrolltext
Version: 0.0.11
Summary: A little toy for scrolling text.
Home-page: https://github.com/jimdeekepler/python-scrolltext
Author: Jim Dee Kepler
Author-email: jimdee@gmail.com
License: GPLv3
Classifier: Development Status :: 3 - Alpha
Classifier: Environment :: Console
Classifier: Environment :: Console :: Curses
Classifier: Intended Audience :: Developers
Classifier: Intended Audience :: Education
Classifier: Intended Audience :: End Users/Desktop
Classifier: Intended Audience :: Other Audience
Classifier: Intended Audience :: System Administrators
Classifier: License :: OSI Approved :: GNU General Public License v3 or later (GPLv3+)
Classifier: Operating System :: OS Independent
Classifier: Programming Language :: Python :: 3
Classifier: Topic :: Games/Entertainment
Classifier: Topic :: Utilities
Requires-Python: >=3.4
License-File: LICENSE
